LICENSE
MANIFEST.in
README.md
README.rst
setup.py
sklearn_fracdiff/__init__.py
sklearn_fracdiff/fracdiff_class.py
sklearn_fracdiff.egg-info/PKG-INFO
sklearn_fracdiff.egg-info/SOURCES.txt
sklearn_fracdiff.egg-info/dependency_links.txt
sklearn_fracdiff.egg-info/requires.txt
sklearn_fracdiff.egg-info/top_level.txt
sklearn_fracdiff.egg-info/zip-safe
test/__init__.py
test/test_fracdiff.py