Metadata-Version: 1.2
Name: sklearn-fracdiff
Version: 0.2.2
Summary: sklearn wrapper for numpy-fracdiff
Home-page: http://github.com/ulf1/sklearn-fracdiff
Author: Ulf Hamster
Author-email: 554c46@gmail.com
License: Apache License 2.0
Platform: UNKNOWN
Requires-Python: >=3.6
